ipex_llm/__init__.py
ipex_llm/convert_model.py
ipex_llm/llm_patching.py
ipex_llm/models.py
ipex_llm/optimize.py
ipex_llm/cli/llm-chat
ipex_llm/cli/llm-chat.ps1
ipex_llm/cli/llm-cli
ipex_llm/cli/llm-cli.ps1
ipex_llm/cli/prompts/chat-with-llm.txt
ipex_llm/ggml/__init__.py
ipex_llm/ggml/convert.py
ipex_llm/ggml/convert_model.py
ipex_llm/ggml/quantize.py
ipex_llm/ggml/model/__init__.py
ipex_llm/ggml/model/bloom/__init__.py
ipex_llm/ggml/model/bloom/bloom.py
ipex_llm/ggml/model/bloom/bloom_cpp.py
ipex_llm/ggml/model/generation/__init__.py
ipex_llm/ggml/model/generation/utils.py
ipex_llm/ggml/model/gptneox/__init__.py
ipex_llm/ggml/model/gptneox/gptneox.py
ipex_llm/ggml/model/gptneox/gptneox_cpp.py
ipex_llm/ggml/model/gptneox/gptneox_types.py
ipex_llm/ggml/model/llama/__init__.py
ipex_llm/ggml/model/llama/llama.py
ipex_llm/ggml/model/llama/llama_cpp.py
ipex_llm/ggml/model/llama/llama_types.py
ipex_llm/ggml/model/starcoder/__init__.py
ipex_llm/ggml/model/starcoder/starcoder.py
ipex_llm/ggml/model/starcoder/starcoder_cpp.py
ipex_llm/gptq/__init__.py
ipex_llm/gptq/convert/__init__.py
ipex_llm/gptq/convert/convert_gptq_to_ggml.py
ipex_llm/langchain/__init__.py
ipex_llm/langchain/embeddings/__init__.py
ipex_llm/langchain/embeddings/bigdlllm.py
ipex_llm/langchain/embeddings/transformersembeddings.py
ipex_llm/langchain/llms/__init__.py
ipex_llm/langchain/llms/bigdlllm.py
ipex_llm/langchain/llms/transformersllm.py
ipex_llm/langchain/llms/transformerspipelinellm.py
ipex_llm/langchain/vllm/__init__.py
ipex_llm/langchain/vllm/vllm.py
ipex_llm/libs/__init__.py
ipex_llm/libs/libbloom-api.so
ipex_llm/libs/libbloom_amx.so
ipex_llm/libs/libbloom_avx.so
ipex_llm/libs/libbloom_avx2.so
ipex_llm/libs/libbloom_avx512.so
ipex_llm/libs/libbloom_avxvnni.so
ipex_llm/libs/libgptneox-api.so
ipex_llm/libs/libgptneox_amx.so
ipex_llm/libs/libgptneox_avx.so
ipex_llm/libs/libgptneox_avx2.so
ipex_llm/libs/libgptneox_avx512.so
ipex_llm/libs/libgptneox_avxvnni.so
ipex_llm/libs/libjemalloc.so
ipex_llm-2.1.0.dist-info/METADATA
ipex_llm-2.1.0.dist-info/WHEEL
ipex_llm-2.1.0.dist-info/entry_points.txt
ipex_llm-2.1.0.dist-info/top_level.txt
ipex_llm-2.1.0.dist-info/RECORD
